{
   "actors": [],
   "countries": [],
   "enb_end_date": "06-Apr-95",
   "enb_long_title": "First Conference of the Parties to the Framework Convention on Climate Change",
   "enb_short_title": "1st COP FCCC",
   "enb_start_date": "06-Apr-95",
   "enb_url": "http://www.iisd.ca/vol12/1219000e.html",
   "id": "1219000e_13",
   "section_title": "ARGENTINA",
   "sentences": [
      "Maria Julia Alsogaray, Minister for the Environment, stated that all countries should design their policies with efficiency in mind.",
      "She reiterated support for a joint implementation pilot phase."
   ],
   "subtype": "",
   "topics": [],
   "type": ""
}