{
   "actors": [],
   "countries": [
      "Qatar"
   ],
   "enb_end_date": "01-Dec-11",
   "enb_long_title": "Durban Climate Change Conference - COP17/CMP7",
   "enb_short_title": "COP17",
   "enb_start_date": "01-Dec-11",
   "enb_url": "http://www.iisd.ca/vol12/enb12526e.html",
   "id": "enb12526e_2",
   "section_title": "DATES AND VENUES OF FUTURE SESSIONS:",
   "sentences": [
      "QATAR, which will host COP 18, said his government will spare no efforts to ensure its success.",
      "The REPUBLIC OF KOREA said that, following lengthy discussions, his country would host the pre-COP ministerial meeting."
   ],
   "subtype": "",
   "topics": [],
   "type": "cop"
}