{
   "actors": [],
   "countries": [],
   "enb_end_date": "17-Jun-11",
   "enb_long_title": "UN Climate Change Conference June 2011",
   "enb_short_title": "SB 34",
   "enb_start_date": "17-Jun-11",
   "enb_url": "http://www.iisd.ca/vol12/enb12512e.html",
   "id": "enb12512e_5",
   "section_title": "HCFC-22/HFC-23",
   "sentences": [
      "The SBSTA adopted conclusions (FCCC/SBSTA/2011/L.6).",
      "Materiality standard under the CDM: The SBSTA adopted conclusions (FCCC/SBSTA/2011/L.11).",
      "Common metrics to calculate the CO2 equivalence of greenhouse gases: The SBSTA adopted conclusions (FCCC/SBSTA/2011/L.8)."
   ],
   "subtype": "",
   "topics": [],
   "type": ""
}