{
   "actors": [],
   "countries": [],
   "enb_end_date": "31-Oct-02",
   "enb_long_title": "Eighth Conference of the Parties to the UN Framework Convention on Climate Change",
   "enb_short_title": "COP-8",
   "enb_start_date": "31-Oct-02",
   "enb_url": "http://www.iisd.ca/vol12/enb12207e.html",
   "id": "enb12207e_1",
   "section_title": "HIGH-LEVEL SEGMENT",
   "sentences": [
      "COP-8 President Baalu opened the high-level segment."
   ],
   "subtype": "PLENARY",
   "topics": [],
   "type": "COP"
}