{
   "actors": [],
   "countries": [],
   "enb_end_date": "19-Dec-09",
   "enb_long_title": "Copenhagen Climate Change Conference",
   "enb_short_title": "COP 15",
   "enb_start_date": "07-Dec-09",
   "enb_url": "http://www.iisd.ca/vol12/enb12459e.html",
   "id": "enb12459e_117",
   "section_title": "REPORTING AND REVIEW OF INFORMATION FROM ANNEX I PARTIES UNDER THE PROTOCOL :",
   "sentences": [
      "This issue (FCCC/SBI/2009/INF.8) was first considered by the SBI on 8 December and then in joint contact group and informal meetings on Annex I reporting under the Convention and Protocol.",
      "The SBI closing plenary adopted the conclusions on 12 December."
   ],
   "subtype": "",
   "topics": [],
   "type": "SBI"
}