{
   "actors": [],
   "countries": [],
   "enb_end_date": "04-Jul-03",
   "enb_long_title": "Workshop on synergies and cooperation with other conventions",
   "enb_short_title": "UNFCCC Workshop",
   "enb_start_date": "02-Jul-03",
   "enb_url": "http://www.iisd.ca/vol12/enb12220e.html",
   "id": "enb12220e_2",
   "section_title": "SBI WORKSHOP",
   "sentences": [
      "During the SBI workshop, participants convened in plenary and working groups to discuss different approaches to addressing synergies, consider synergies from the perspective of preserving biodiversity and combating desertification, and identify possible synergies and joint action with other MEAs."
   ],
   "subtype": "",
   "topics": [],
   "type": "SBI"
}