{
   "actors": [],
   "countries": [],
   "enb_end_date": "25-May-05",
   "enb_long_title": "United Nations Framework Convention on Climate Change: Twenty-Second Session of the Subsidiary Bodies",
   "enb_short_title": "UNFCCC SB 22",
   "enb_start_date": "25-May-05",
   "enb_url": "http://www.iisd.ca/vol12/enb12267e.html",
   "id": "enb12267e_1",
   "section_title": "SBSTA",
   "sentences": [
      "On Tuesday morning, a SBSTA round table was held on Annex I Parties` policies and measures (P&Ms).",
      "The event, which was mandated by SBSTA 20, involved presentations and discussions aimed at sharing information and exchanging experiences in implementing P&Ms.",
      "The meeting was divided into three parts: domestic aspects; international aspects; and cross-cutting issues.",
      "Jonathan Pershing, World Resources Institute, facilitated the meeting."
   ],
   "subtype": "",
   "topics": [],
   "type": "SBSTA"
}