{
   "actors": [],
   "countries": [],
   "enb_end_date": "06-Apr-95",
   "enb_long_title": "First Conference of the Parties to the Framework Convention on Climate Change",
   "enb_short_title": "1st COP FCCC",
   "enb_start_date": "06-Apr-95",
   "enb_url": "http://www.iisd.ca/vol12/1219000e.html",
   "id": "1219000e_29",
   "section_title": "BURKINA FASO",
   "sentences": [
      "Anatole Tiendrebeogo, Minister of the Environment and Tourism, expressed faith in international solidarity and described his country's efforts on climate change."
   ],
   "subtype": "",
   "topics": [],
   "type": ""
}