{
   "actors": [],
   "countries": [],
   "enb_end_date": "28-Apr-06",
   "enb_long_title": "IPCC-25",
   "enb_short_title": "IPCC-25",
   "enb_start_date": "26-Apr-06",
   "enb_url": "http://www.iisd.ca/vol12/enb12295e.html",
   "id": "enb12295e_20",
   "section_title": "Final Outcome",
   "sentences": [
      "The rules of procedures for the election of the IPCC Bureau and any Task Force Bureau adopted by the Panel include rules relating to: the composition of the IPCC Bureau and any Task Force Bureau, including composition with regard to geographical representation; terms of appointment; general principles of elections; nominations; voting procedures; and amendments and suspensions."
   ],
   "subtype": "",
   "topics": [],
   "type": ""
}