{
   "actors": [],
   "countries": [],
   "enb_end_date": "12-Dec-08",
   "enb_long_title": "UN Climate Change Conference - Pozna\u0144",
   "enb_short_title": "COP 14",
   "enb_start_date": "01-Dec-08",
   "enb_url": "http://www.iisd.ca/vol12/enb12395e.html",
   "id": "enb12395e_11",
   "section_title": "SBI Conclusions",
   "sentences": [
      "In its conclusions (FCCC/SBI/2008/L.21), the SBI, inter alia , welcomes information submitted by parties and intergovernmental organizations on the implementation of NAPAs, and notes with appreciation that donors have provided US$172 million to the LDC Fund."
   ],
   "subtype": "",
   "topics": [],
   "type": ""
}