{
   "actors": [],
   "countries": [],
   "enb_end_date": "02-Jun-15",
   "enb_long_title": "Bonn Climate Change Conference - June 2015",
   "enb_short_title": "SB 42",
   "enb_start_date": "02-Jun-15",
   "enb_url": "http://www.iisd.ca/vol12/enb12629e.html",
   "id": "enb12629e_13",
   "section_title": "Multilateral Assessment Working Group Session under the Independent Assessment Report (IAR) Process",
   "sentences": [
      "Parties took note of information provided by SBI Chair Yauvoli, who will also chair the two-day multilateral assessment session."
   ],
   "subtype": "",
   "topics": [],
   "type": ""
}