{
   "actors": [],
   "countries": [],
   "enb_end_date": "28-Sep-09",
   "enb_long_title": "Bangkok Climate Change Talks - 2009",
   "enb_short_title": "AWGs",
   "enb_start_date": "28-Sep-09",
   "enb_url": "http://www.iisd.ca/vol12/enb12428e.html",
   "id": "enb12428e_9",
   "section_title": "UN HIGH-LEVEL EVENT ON CLIMATE CHANGE:",
   "sentences": [
      "On 22 September 2009, UN Secretary-General Ban Ki-moon hosted an all-day high-level event on climate change for Heads of State and Government at UN Headquarters in New York.",
      "According to the Secretary-General s summary, the summit sent a clear message on the need for a comprehensive deal in Copenhagen and on ensuring: enhanced action to assist the most vulnerable in adaptation; ambitious emission reduction targets for industrialized countries; nationally appropriate mitigation actions (NAMAs) by developing countries with necessary support; significantly scaled-up financial and technological resources; and an equitable governance structure."
   ],
   "subtype": "",
   "topics": [],
   "type": "working group"
}