{
   "actors": [],
   "countries": [
      "Papua New Guinea"
   ],
   "enb_end_date": "09-Dec-05",
   "enb_long_title": "Eleventh session of the Conference of the Parties to the Climate Change Convention and first meeting of the Parties to the Kyoto Protocol",
   "enb_short_title": "UNFCCC COP 11 and COP/MOP 1",
   "enb_start_date": "28-Nov-05",
   "enb_url": "http://www.iisd.ca/vol12/enb12291e.html",
   "id": "enb12291e_116",
   "section_title": "Avoided Deforestation",
   "sentences": [
      "Several parties discussed a proposal by Papua New Guinea to provide incentives to developing countries for avoided deforestation."
   ],
   "subtype": "",
   "topics": [],
   "type": ""
}