{
   "actors": [],
   "countries": [
      "Norway",
      "Saudi Arabia",
      "Tajikistan"
   ],
   "enb_end_date": "08-Dec-12",
   "enb_long_title": "Doha Climate Change Conference - November 2012",
   "enb_short_title": "COP 18",
   "enb_start_date": "26-Nov-12",
   "enb_url": "http://www.iisd.ca/vol12/enb12567e.html",
   "id": "enb12567e_28",
   "section_title": "Compliance Committee Report",
   "sentences": [
      "This issue (FCCC/KP/CMP/2012/6) was taken up by the CMP plenary on 28 November.",
      "Compliance Committee Co-Chair Khalid Abuleif (Saudi Arabia) presented the report of the Committee, noting that 2012 was the busiest year to date for the Committee s Enforcement Branch and a significant year for the Facilitative Branch.",
      "Ilhomjon Rajabov (Tajikistan) and Christina Voigt (Norway) facilitated informal consultations."
   ],
   "subtype": "",
   "topics": [
      "UNFCCC Functioning"
   ],
   "type": ""
}