{
  "countries": [], 
  "topics": [], 
  "section_title": "CANADA", 
  "enb_start_date": "18-Jul-96", 
  "enb_short_title": "2nd COP FCCC", 
  "subtype": "", 
  "actors": [], 
  "sentences": [
    "Sergio Marchi, Minister of the Environment, strongly supported the SAR as a basis for urgent action, noting that uncertainties regarding the rate and level of climate change are not grounds for inaction.", 
    "He said countries need to work 'harder, faster and smarter' and encouraged the development and use of clean technologies, projects aimed at energy efficiency and the involvement of governments, international institutions, industry and NGOs in an open and transparent process.", 
    "He called for the establishment of targets for the year 2000 and beyond."
  ], 
  "enb_url": "http://www.iisd.ca/vol12/1236000e.html", 
  "enb_long_title": "Second Conference of the Parties to the Framework Convention on Climate Change", 
  "type": "", 
  "id": "1236000e_10", 
  "enb_end_date": "18-Jul-96"
}