{
  "countries": [
    "Nepal", 
    "Bangladesh"
  ], 
  "topics": [], 
  "section_title": "ORGANIZATIONAL MATTERS:", 
  "enb_start_date": "14-Dec-09", 
  "enb_short_title": "COP 15", 
  "subtype": "", 
  "actors": [], 
  "sentences": [
    "The SBSTA agreed to elect Mihir Kanti Majumder (Bangladesh) as Vice-Chair and Purushottam Ghimire (Nepal) as Rapporteur."
  ], 
  "enb_url": "http://www.iisd.ca/vol12/enb12454e.html", 
  "enb_long_title": "Copenhagen Climate Change Conference", 
  "type": "sbsta", 
  "id": "enb12454e_5", 
  "enb_end_date": "14-Dec-09"
}