{
  "countries": [], 
  "topics": [
    "UNFCCC and Kyoto Protocol Functioning"
  ], 
  "section_title": "Budget performance for the biennium 2010-2011", 
  "enb_start_date": "10-Jun-11", 
  "enb_short_title": "SB 34", 
  "subtype": "", 
  "actors": [], 
  "sentences": [
    "The Secretariat introduced the issues (FCCC/SBI/2011/INF.3 and INF.5).", 
    "SBI Chair Owen-Jones will draft conclusions."
  ], 
  "enb_url": "http://www.iisd.ca/vol12/enb12506e.html", 
  "enb_long_title": "UN Climate Change Conference June 2011", 
  "type": "", 
  "id": "enb12506e_5", 
  "enb_end_date": "10-Jun-11"
}