{
  "countries": [], 
  "topics": [
    "UNFCCC and Kyoto Protocol Functioning"
  ], 
  "section_title": "COP/MOP Decision", 
  "enb_start_date": "29-Nov-10", 
  "enb_short_title": "COP 16", 
  "subtype": "", 
  "actors": [], 
  "sentences": [
    "In its decision (FCCC/SBI/2010/L.24/Add.2), the COP/MOP, inter alia , urges parties to further contribute to the Trust Fund for Participation in the UNFCCC Process and the Trust Fund for Supplementary Activities.", 
    "Privileges and Immunities: This issue (FCCC/SBI/2010/10) was first considered in SBI plenary on 30 November.", 
    "The SBI agreed to continue consideration of this issue at SBI 34."
  ], 
  "enb_url": "http://www.iisd.ca/vol12/enb12498e.html", 
  "enb_long_title": "Canc\u00fan Climate Change Conference", 
  "type": "", 
  "id": "enb12498e_88", 
  "enb_end_date": "11-Dec-10"
}