{
  "countries": [
    "Germany"
  ], 
  "topics": [
    "UNFCCC and Kyoto Protocol Functioning"
  ], 
  "section_title": "COP/MOP Decision", 
  "enb_start_date": "07-Dec-09", 
  "enb_short_title": "COP 15", 
  "subtype": "", 
  "actors": [], 
  "sentences": [
    "In its decision (FCCC/SBI/2009/L.21/Add.2) the COP/MOP calls uponparties that have not paid their contributions to the core budget and the international transaction log to do so and expresses appreciationfor the contributions received from parties to the Trust Fund for Participation in the UNFCCC Process and to the Trust Fund for Supplementary Activities.", 
    "The COP/MOP reiteratesits appreciation to Germany for its annual voluntary contribution to the core budget of \u00e2\u0082\u00ac766,938 and its special contribution of \u00e2\u0082\u00ac1,789,522 as host country to the Secretariat."
  ], 
  "enb_url": "http://www.iisd.ca/vol12/enb12459e.html", 
  "enb_long_title": "Copenhagen Climate Change Conference", 
  "type": "", 
  "id": "enb12459e_59", 
  "enb_end_date": "19-Dec-09"
}