{
  "countries": [], 
  "topics": [], 
  "section_title": "COMPLIANCE", 
  "enb_start_date": "07-Dec-05", 
  "enb_short_title": "UNFCCC COP 11 and COP/MOP 1", 
  "subtype": "", 
  "actors": [], 
  "sentences": [
    "Co-Chair Dovland noted that an agreement had not been possible even after several informal consultations.", 
    "He explained that the key differences still related to how the compliance mechanism should be adopted at COP/MOP 1, and how the process will continue regarding an amendment to the Protocol to make the system legally binding.", 
    "He said the outstanding questions would be solved either through further informal consultations or by President Dion.", 
    "Although differences narrowed, no agreement was reached during informal consultations on Tuesday afternoon."
  ], 
  "enb_url": "http://www.iisd.ca/vol12/enb12288e.html", 
  "enb_long_title": "Eleventh session of the Conference of the Parties to the Climate Change Convention and first meeting of the Parties to the Kyoto Protocol", 
  "type": "", 
  "id": "enb12288e_27", 
  "enb_end_date": "07-Dec-05"
}