{
  "countries": [], 
  "topics": [], 
  "section_title": "SBSTA Conclusions", 
  "enb_start_date": "06-Jun-11", 
  "enb_short_title": "SB 34", 
  "subtype": "", 
  "actors": [], 
  "sentences": [
    "In its conclusions (FCCC/SBSTA/2011/L.5), the SBSTA notes: the information paper prepared by the Secretariat summarizing activities of the UN and other intergovernmental organizations contributing to the Convention; the focus of the Secretariat s cooperative activities and initiatives; and statements by the CBD and UNCCD on their efforts to address climate change."
  ], 
  "enb_url": "http://www.iisd.ca/vol12/enb12513e.html", 
  "enb_long_title": "UN Climate Change Conference June 2011", 
  "type": "", 
  "id": "enb12513e_36", 
  "enb_end_date": "17-Jun-11"
}