{
  "countries": [], 
  "topics": [
    "National Communications & Inventories"
  ], 
  "section_title": "SBI Conclusions:", 
  "enb_start_date": "17-Jun-02", 
  "enb_short_title": "SB-16", 
  "subtype": "", 
  "actors": [], 
  "sentences": [
    "The SBI conclusions (FCCC/SBI/2002/L.4) take note of the need to support the implementation of capacity-building activities relating to the preparation of national inventories and establishment of national systems, and include an invitation for Parties to submit their views on the implementation of national capacity needs self-assessments funded by the GEF."
  ], 
  "enb_url": "http://www.iisd.ca/vol12/enb12200e.html", 
  "enb_long_title": "Sixteenth Sessions of the Subsidiary Bodies", 
  "type": "", 
  "id": "enb12200e_63", 
  "enb_end_date": "17-Jun-02"
}