{
  "countries": [], 
  "topics": [
    "UNFCCC and Kyoto Protocol Functioning"
  ], 
  "section_title": "Outcome", 
  "enb_start_date": "01-Jun-15", 
  "enb_short_title": "SB 42", 
  "subtype": "", 
  "actors": [], 
  "sentences": [
    "In its conclusions (FCCC/SBI/2015/L.4), the SBI, inter alia: expresses satisfaction with the new World Conference Center Bonn; requests the Secretariat to maximize the combined use of the Secretariat\u2019s office facilities and the conference centre for UNFCCC sessions and meetings; takes note of reports on progress on the design of an extension building on the United Nations Campus; requests the Secretariat to continue to update parties on the UNFCCC website about the implementation of the headquarters agreement; and invites the host government and the UNFCCC Executive Secretary to report to SBI 46 on progress."
  ], 
  "enb_url": "http://www.iisd.ca/vol12/enb12638e.html", 
  "enb_long_title": "Bonn Climate Change Conference - June 2015", 
  "type": "", 
  "id": "enb12638e_73", 
  "enb_end_date": "11-Jun-15"
}