{
  "countries": [], 
  "topics": [
    "Technology Transfer"
  ], 
  "section_title": "COP Decision", 
  "enb_start_date": "28-Nov-11", 
  "enb_short_title": "COP17", 
  "subtype": "", 
  "actors": [], 
  "sentences": [
    "In Section VIII of the decision (FCCC/AWGLCA/2011/L.4), the COP invites Annex I parties, that are in a position to do so, to make available the capacity-building, financial, technical and technology transfer assistance for Annex I parties with EIT; and agrees to continue with the discussion on modalities for the provision of support for mitigation, adaptation, technology development and transfer, capacity-building and finance to parties whose special circumstances are recognized by the COP."
  ], 
  "enb_url": "http://www.iisd.ca/vol12/enb12534e.html", 
  "enb_long_title": "Durban Climate Change Conference - COP17/CMP7", 
  "type": "", 
  "id": "enb12534e_110", 
  "enb_end_date": "09-Dec-11"
}