{
  "countries": [], 
  "topics": [], 
  "section_title": "CCS UNDER THE CDM (SBSTA):", 
  "enb_start_date": "05-Dec-08", 
  "enb_short_title": "COP 14", 
  "subtype": "", 
  "actors": [
    "European Union"
  ], 
  "sentences": [
    "In a contact group and informal consultations, delegates considered draft text setting out various options, including an EU proposal for a pilot phase.", 
    "Some parties supported CCS under the CDM, while others said it should not be included in the current commitment period, but might be considered at a later stage."
  ], 
  "enb_url": "http://www.iisd.ca/vol12/enb12389e.html", 
  "enb_long_title": "UN Climate Change Conference - Pozna\u0144", 
  "type": "", 
  "id": "enb12389e_3", 
  "enb_end_date": "05-Dec-08"
}