{
  "countries": [
    "Canada", 
    "Czech Republic", 
    "Lithuania", 
    "Malta", 
    "Slovakia", 
    "Ireland", 
    "Norway", 
    "Australia", 
    "Iceland", 
    "Slovenia", 
    "Germany", 
    "Russian Federation", 
    "Ukraine", 
    "Poland", 
    "Belgium", 
    "Liechtenstein", 
    "Monaco", 
    "Bulgaria", 
    "Romania", 
    "Estonia", 
    "United Kingdom", 
    "Hungary"
  ], 
  "topics": [], 
  "section_title": "Multilateral Assessment Working Group Session under the International Assessment and Review (IAR) Process", 
  "enb_start_date": "01-Jun-15", 
  "enb_short_title": "SB 42", 
  "subtype": "", 
  "actors": [], 
  "sentences": [
    "This item was first considered on Monday, 1 June, in plenary, with parties taking note of information provided by SBI Chair Yauvoli, who chaired the two-day multilateral assessment session. On Thursday, 4 June, Australia, Belgium, Bulgaria, Canada, the Czech Republic, Estonia, Germany, Hungary, Iceland and Ireland were assessed.", 
    "A summary of the discussions is available at: http://www.iisd.ca/vol12/enb12632e.html On Friday, 5 June, Liechtenstein, Lithuania, Malta, Monaco, Norway, Poland, Romania, the Russian Federation, Slovakia, Slovenia, Ukraine and the United Kingdom were assessed.", 
    "A summary of the discussions is available at: http://www.iisd.ca/vol12/enb12633e.html"
  ], 
  "enb_url": "http://www.iisd.ca/vol12/enb12638e.html", 
  "enb_long_title": "Bonn Climate Change Conference - June 2015", 
  "type": "", 
  "id": "enb12638e_28", 
  "enb_end_date": "11-Jun-15"
}