{
  "countries": [
    "Canada", 
    "Bolivia", 
    "Burkina Faso"
  ], 
  "topics": [
    "Adaptation"
  ], 
  "section_title": "NATIONAL ADAPTATION PLANS (NAPs)", 
  "enb_start_date": "02-Jun-15", 
  "enb_short_title": "SB 42", 
  "subtype": "", 
  "actors": [], 
  "sentences": [
    "Adaptation Committee Co-Chair Juan Hoffmeister (Bolivia) provided an oral update in response to the mandate outlined in Decision 3/CP.20 paragraph 11 (FCCC/SBI/2015/INF.6).", 
    "Informal consultations will be co-facilitated by Mamadou Honadia (Burkina Faso) and Beth Lavender (Canada)."
  ], 
  "enb_url": "http://www.iisd.ca/vol12/enb12629e.html", 
  "enb_long_title": "Bonn Climate Change Conference - June 2015", 
  "type": "", 
  "id": "enb12629e_17", 
  "enb_end_date": "02-Jun-15"
}