{
  "countries": [], 
  "topics": [
    "Financial Mechanisms and Funds"
  ], 
  "section_title": "SB-18", 
  "enb_start_date": "28-Jun-04", 
  "enb_short_title": "UNFCCC SB-20", 
  "subtype": "", 
  "actors": [], 
  "sentences": [
    "Delegates to SB-18 met in Bonn from 4-13 June 2003.", 
    "Parties continued to address issues under negotiation since COP-8 and prepare for the Protocol\u0092s entry into force.", 
    "Conclusions were agreed on a number of agenda items, including on Protocol Articles 5, 7 and 8.", 
    "The issue of the Secretariat\u0092s programme budget for 2004-5 and the Special Climate Change Fund proved to be particularly difficult, and discussions were left unfinished until COP-9."
  ], 
  "enb_url": "http://www.iisd.ca/vol12/enb12242e.html", 
  "enb_long_title": "Twentieth Session of the Subsidiary Bodies to the UN Framework Convention on Climate Change", 
  "type": "", 
  "id": "enb12242e_8", 
  "enb_end_date": "28-Jun-04"
}