{
  "countries": [], 
  "topics": [], 
  "section_title": "SBI Conclusions", 
  "enb_start_date": "29-Nov-10", 
  "enb_short_title": "COP 16", 
  "subtype": "", 
  "actors": [], 
  "sentences": [
    "In its conclusions (FCCC/SBI/2010/L.28), the SBI: requests the LEG to keep SBI informed of the LEG s efforts in implementing its 2011-2015 work programme; invites parties in a position to do so to continue to provide resources in support of the implementation of the LEG work programme; and recommends a draft decision on this matter for adoption by the COP."
  ], 
  "enb_url": "http://www.iisd.ca/vol12/enb12498e.html", 
  "enb_long_title": "Canc\u00fan Climate Change Conference", 
  "type": "", 
  "id": "enb12498e_70", 
  "enb_end_date": "11-Dec-10"
}