{
  "countries": [], 
  "topics": [
    "UNFCCC and Kyoto Protocol Functioning"
  ], 
  "section_title": "SBSTA Conclusions", 
  "enb_start_date": "14-May-12", 
  "enb_short_title": "SB 36", 
  "subtype": "", 
  "actors": [], 
  "sentences": [
    "In its conclusions (FCCC/SBSTA/2012/ L.7), the SBSTA, inter alia : welcomes the further improvements made by the Secretariat to the greenhouse gas data interface; and agrees to consider at SBSTA 38 matters relating to further development of the interface in order to accommodate relevant changes relating to the forthcoming use of the revised reporting guidelines by Annex I parties."
  ], 
  "enb_url": "http://www.iisd.ca/vol12/enb12546e.html", 
  "enb_long_title": "Bonn Climate Change Conference - May 2012", 
  "type": "", 
  "id": "enb12546e_35", 
  "enb_end_date": "25-May-12"
}